LICENSE
wikiusers/__init__.py
wikiusers/dataloader/__init__.py
wikiusers/dataloader/mhdloader.py
wikiusers/logger/__init__.py
wikiusers/logger/logger.py
wikiusers/postprocessor/__init__.py
wikiusers/postprocessor/processor.py
wikiusers/postprocessor/utils/__init__.py
wikiusers/postprocessor/utils/batcher.py
wikiusers/postprocessor/utils/elaborator/__init__.py
wikiusers/postprocessor/utils/elaborator/sex.py
wikiusers/postprocessor/utils/elaborator/users.py
wikiusers/postprocessor/utils/uploader.py
wikiusers/rawprocessor/__init__.py
wikiusers/rawprocessor/processor.py
wikiusers/rawprocessor/utils/__init__.py
wikiusers/rawprocessor/utils/analyzer.py
wikiusers/rawprocessor/utils/keys.py
wikiusers/rawprocessor/utils/misc.py
wikiusers/rawprocessor/utils/parser.py
wikiusers/rawprocessor/utils/uploader.py
wikiusers/settings/__init__.py
wikiusers/settings/settings.py
wikiusers-1.2.0.dist-info/LICENSE
wikiusers-1.2.0.dist-info/WHEEL
wikiusers-1.2.0.dist-info/METADATA
wikiusers-1.2.0.dist-info/RECORD
